airflow_markdown_extension/__init__.py
airflow_markdown_extension/utils.py
airflow_markdown_extension/fences/__init__.py
airflow_markdown_extension/fences/airflow_dag.py
airflow_markdown_extension-0.1.1.dist-info/METADATA
airflow_markdown_extension-0.1.1.dist-info/WHEEL
airflow_markdown_extension-0.1.1.dist-info/RECORD
